{
  "notes": [
    {
      "id": "0",
      "title": "Going for a jog",
      "text": "Go for a run around 3pm"
    },
    {
      "id": "1",
      "title": "play the game",
      "text": "Play the xbox around 5pm"
    },
    {
      "id": "2",
      "title": "Drink some water",
      "text": "Drink water every 2 hours"
    },
    {
      "id": "3",
      "title": "buy food for tonight",
      "text": "go to the supermarket for food"
    },
    {
      "id": "4",
      "title": "buy food for tonight",
      "text": "go to the supermarket for food"
    },
    {
      "title": ",m",
      "text": "lk",
      "id": "5"
    }
  ]
}